khanbox/__init__.py
khanbox/lego.py
khanbox/pattern.py
khanbox/xlsx.py
khanbox-0.1.0.dist-info/WHEEL
khanbox-0.1.0.dist-info/METADATA
khanbox-0.1.0.dist-info/RECORD
