Metadata-Version: 2.1
Name: khanbox
Version: 0.1.0
Summary: 
Author: Khalid
Author-email: khalidck@gmail.com
Requires-Python: >=3.7,<4.0
Classifier: Programming Language :: Python :: 3
Classifier: Programming Language :: Python :: 3.7
Classifier: Programming Language :: Python :: 3.8
Requires-Dist: XlsxWriter (>=1.2.8,<2.0.0)
Requires-Dist: pandas (>=1.0.3,<2.0.0)
